LICENSE.txt
MANIFEST.in
README.rst
pyproject.toml
requirements.txt
setup.py
test-requirements.txt
trackhub/__init__.py
trackhub/assembly.py
trackhub/base.py
trackhub/compatibility.py
trackhub/constants.py
trackhub/genome.py
trackhub/genomes_file.py
trackhub/groups.py
trackhub/helpers.py
trackhub/hub.py
trackhub/parse.py
trackhub/parsed_params.py
trackhub/settings.py
trackhub/track.py
trackhub/trackdb.py
trackhub/trackhub_from_excel
trackhub/upload.py
trackhub/validate.py
trackhub/version.py
trackhub.egg-info/PKG-INFO
trackhub.egg-info/SOURCES.txt
trackhub.egg-info/dependency_links.txt
trackhub.egg-info/requires.txt
trackhub.egg-info/top_level.txt
trackhub/test/__init__.py
trackhub/test/construct_example_data.py
trackhub/test/construct_example_genome.py
trackhub/test/deprecated_upload_test.py
trackhub/test/test_add_tracks.py
trackhub/test/test_assembly.py
trackhub/test/test_components.py
trackhub/test/test_example_data.py
trackhub/test/test_supertrack.py
trackhub/test/upload_test.py
trackhub/test/data/.gitignore
trackhub/test/data/__init__.py
trackhub/test/data/download_ucsc_examples.sh
trackhub/test/data/example.xlsx
trackhub/test/data/newOrg1.2bit
trackhub/test/data/random-hg38-0.bigBed
trackhub/test/data/random-hg38-1.bigBed
trackhub/test/data/random-hg38-2.bigBed
trackhub/test/data/random-no1-0.bigBed
trackhub/test/data/random-no1-1.bigBed
trackhub/test/data/random-no1-2.bigBed
trackhub/test/data/sine-hg38-0.bedgraph.bw
trackhub/test/data/sine-hg38-1.bedgraph.bw
trackhub/test/data/sine-hg38-2.bedgraph.bw
trackhub/test/data/sine-no1-100.bedgraph.bw
trackhub/test/data/sine-no1-1000.bedgraph.bw